yamodb/__init__.py
yamodb/yamodb.py
yamodb/placeholder_database/first-names.json
yamodb/placeholder_database/middle-names.json
yamodb-0.0.4.dist-info/METADATA
yamodb-0.0.4.dist-info/WHEEL
yamodb-0.0.4.dist-info/top_level.txt
yamodb-0.0.4.dist-info/RECORD
