Metadata-Version: 2.2
Name: yamodb
Version: 0.0.4
Summary: powerful and lightweight library designed for data and database.
Home-page: https://github.com/svidaniya/yamodb
Author: svidaniya
Author-email: seuemail@example.com
Classifier: Programming Language :: Python :: 3
Classifier: License :: OSI Approved :: MIT License
Classifier: Operating System :: OS Independent
Requires-Python: >=3.6
Requires-Dist: cryptography==3.4
Requires-Dist: python-dateutil==2.9.0.post0
Requires-Dist: PyYAML==6.0.2
Requires-Dist: six==1.17.0
Requires-Dist: yamtimes==0.0.1
Dynamic: author
Dynamic: author-email
Dynamic: classifier
Dynamic: description
Dynamic: description-content-type
Dynamic: home-page
Dynamic: requires-dist
Dynamic: requires-python
Dynamic: summary
